nssurge_api/__init__.py
nssurge_api/api.py
nssurge_api/types.py
nssurge_api-0.2.17.dist-info/LICENSE
nssurge_api-0.2.17.dist-info/METADATA
nssurge_api-0.2.17.dist-info/WHEEL
nssurge_api-0.2.17.dist-info/entry_points.txt
nssurge_api-0.2.17.dist-info/RECORD
