Metadata-Version: 2.1
Name: nssurge-api
Version: 0.2.17
Summary: NSSurge HTTP API for Python
Home-page: https://github.com/tddschn/nssurge-api
License: MIT
Keywords: nssurge,api,aiohttp
Author: Xinyuan Chen
Author-email: 45612704+tddschn@users.noreply.github.com
Requires-Python: >=3.11,<4.0
Classifier: License :: OSI Approved :: MIT License
Classifier: Operating System :: OS Independent
Classifier: Programming Language :: Python :: 3
Classifier: Programming Language :: Python :: 3.11
Classifier: Topic :: Internet :: WWW/HTTP
Requires-Dist: aiohttp (>=3.8.1,<4.0.0)
Requires-Dist: typing-extensions (>=4.2.0,<5.0.0)
Project-URL: Bug Tracker, https://github.com/tddschn/nssurge-api/issues
Project-URL: Repository, https://github.com/tddschn/nssurge-api
